hubspot/__init__.py
hubspot/client.py
hubspot_connector-0.0.3.dist-info/METADATA
hubspot_connector-0.0.3.dist-info/WHEEL
hubspot_connector-0.0.3.dist-info/top_level.txt
hubspot_connector-0.0.3.dist-info/RECORD
