Metadata-Version: 2.4
Name: hubspot-connector
Version: 0.0.3
Summary: A utility class to interact with Hubspot using OAuth 2.0 credentials.
Author: Mukhtar
Author-email: mrather552@gmail.com
Requires-Dist: requests
Dynamic: author
Dynamic: author-email
Dynamic: description
Dynamic: description-content-type
Dynamic: requires-dist
Dynamic: summary
